callonce/__init__.py
callonce/_version.py
callonce/callonce.py
callonce-0.1.0.dist-info/LICENSE
callonce-0.1.0.dist-info/METADATA
callonce-0.1.0.dist-info/WHEEL
callonce-0.1.0.dist-info/top_level.txt
callonce-0.1.0.dist-info/RECORD
