Metadata-Version: 2.1
Name: callonce
Version: 0.1.0
Summary: make a function callable for once or N times
Home-page: https://github.com/SunDoge/callonce
Author: SunDoge
Author-email: 384813529@qq.com
License: UNKNOWN
Platform: UNKNOWN
Requires-Python: >=3.6
